oai_dataset_processor/__init__.py
oai_dataset_processor/models/sample_types.py
oai_dataset_processor/processors/openai_processor.py
oai_dataset_processor/relational_db/orm_layout.py
oai_dataset_processor/relational_db/storage_handler.py
oai_dataset_processor/utils/sample_creation.py
oai_dataset_processor-0.1.4.dist-info/LICENSE
oai_dataset_processor-0.1.4.dist-info/METADATA
oai_dataset_processor-0.1.4.dist-info/WHEEL
oai_dataset_processor-0.1.4.dist-info/top_level.txt
oai_dataset_processor-0.1.4.dist-info/RECORD
