Metadata-Version: 2.2
Name: oai_dataset_processor
Version: 0.1.4
Summary: A sample dataset processor for evaluating datasets.
Author-email: Ben Gitter <gitterbd@gmail.com>
License: Apache-2.0
Project-URL: Homepage, https://github.com/gittb/oai_dataset_processor
Project-URL: Bug Tracker, https://github.com/gittb/oai_dataset_processor/issues
Classifier: Development Status :: 3 - Alpha
Classifier: Intended Audience :: Developers
Classifier: License :: OSI Approved :: Apache Software License
Classifier: Programming Language :: Python :: 3.11
Requires-Python: >=3.11
License-File: LICENSE
Requires-Dist: openai>=1.57.0
Requires-Dist: tqdm>=4.65.0
Requires-Dist: pandas>=2.0.0
Requires-Dist: sqlalchemy>=2.0.0
Requires-Dist: pydantic>=2.10.0
Provides-Extra: dev
Requires-Dist: mypy; extra == "dev"
Requires-Dist: ruff; extra == "dev"
